emails/__init__.py
emails/admin.py
emails/apps.py
emails/backend.py
emails/models.py
emails/version.py
emails/migrations/0001_initial.py
emails/migrations/0002_added_default_replyto.py
emails/migrations/0003_added_notes.py
emails/migrations/0004_base_manager_name.py
emails/migrations/0005_string_fields.py
emails/migrations/__init__.py
django_fluo_emails-0.3.dist-info/COPYING
django_fluo_emails-0.3.dist-info/METADATA
django_fluo_emails-0.3.dist-info/WHEEL
django_fluo_emails-0.3.dist-info/top_level.txt
django_fluo_emails-0.3.dist-info/RECORD
